odatse/extra/XAFS/__init__.py
odatse/extra/XAFS/_main.py
odatse/extra/XAFS/feff.py
odatse/extra/XAFS/input.py
odatse/extra/XAFS/output.py
odatse/extra/XAFS/parameter.py
odatse_xafs-1.0.0.dist-info/LICENSE
odatse_xafs-1.0.0.dist-info/METADATA
odatse_xafs-1.0.0.dist-info/WHEEL
odatse_xafs-1.0.0.dist-info/entry_points.txt
odatse_xafs-1.0.0.dist-info/RECORD
