Metadata-Version: 2.3
Name: odatse-XAFS
Version: 1.0.0
Summary: PTRF-XAFS solver module for ODAT-SE: data-analysis software of quantum beam diffraction experiments for 2D material structure
License: GPL-3.0-or-later
Author: 2DMAT developers
Author-email: 2dmat-dev@issp.u-tokyo.ac.jp
Requires-Python: >=3.9
Classifier: License :: OSI Approved :: GNU General Public License v3 or later (GPLv3+)
Classifier: Programming Language :: Python :: 3
Classifier: Programming Language :: Python :: 3.9
Classifier: Programming Language :: Python :: 3.10
Classifier: Programming Language :: Python :: 3.11
Classifier: Programming Language :: Python :: 3.12
Classifier: Programming Language :: Python :: 3.13
Requires-Dist: ODAT-SE (>=3,<4)
Requires-Dist: numpy (>=1.14,<2.0)
Requires-Dist: pydantic (>=2,<3)
Project-URL: Repository, https://github.com/2DMAT/odatse-XAFS
